{
  "tokens": [
    {
      "id": 0,
      "description": "My NFT",
      "image": "https://github.com/4ix/nfttest/raw/master/image/test.png",
      "name": "Jaime 0 png"
    },
    {
      "id": 1,
      "description": "My NFT",
      "image": "https://github.com/4ix/nfttest/raw/master/image/test.svg",
      "name": "Jaime 1 svg"
    },
    {
      "id": 2,
      "description": "My NFT",
      "image": "https://github.com/4ix/nfttest/raw/master/image/test.jpg",
      "name": "Jaime 2 jpg"
    }
  ]
}